ssh2/c_ssh2.pxd
ssh2/publickey.pxd
ssh2/_version.py
ssh2/listener.cpython-311-i386-linux-gnu.so
ssh2/__init__.pxd
ssh2/libssh2.so
ssh2/__init__.py
ssh2/sftp.pxd
ssh2/knownhost.cpython-311-i386-linux-gnu.so
ssh2/channel.pxd
ssh2/utils.cpython-311-i386-linux-gnu.so
ssh2/c_pkey.pxd
ssh2/error_codes.cpython-311-i386-linux-gnu.so
ssh2/pkey.pxd
ssh2/session.pxd
ssh2/sftp_handle.cpython-311-i386-linux-gnu.so
ssh2/knownhost.pxd
ssh2/fileinfo.cpython-311-i386-linux-gnu.so
ssh2/error_codes.pxd
ssh2/sftp.cpython-311-i386-linux-gnu.so
ssh2/statinfo.cpython-311-i386-linux-gnu.so
ssh2/exceptions.cpython-311-i386-linux-gnu.so
ssh2/sftp_handle.pxd
ssh2/c_sftp.pxd
ssh2/listener.pxd
ssh2/fileinfo.pxd
ssh2/agent.pxd
ssh2/publickey.cpython-311-i386-linux-gnu.so
ssh2/session.cpython-311-i386-linux-gnu.so
ssh2/libssh2.so.1
ssh2/c_stat.pxd
ssh2/utils.pxd
ssh2/pkey.cpython-311-i386-linux-gnu.so
ssh2/agent.cpython-311-i386-linux-gnu.so
ssh2/statinfo.pxd
ssh2/libssh2.so.1.0.1
ssh2/channel.cpython-311-i386-linux-gnu.so
ssh2_python312-0.1.1.dist-info/RECORD
ssh2_python312-0.1.1.dist-info/COPYING
ssh2_python312-0.1.1.dist-info/METADATA
ssh2_python312-0.1.1.dist-info/WHEEL
ssh2_python312-0.1.1.dist-info/top_level.txt
ssh2_python312-0.1.1.dist-info/LICENSE
ssh2_python312.libs/libselinux-c9aa910a.so.1
ssh2_python312.libs/libpcre-863f8bd5.so.1.2.0
ssh2_python312.libs/libcom_err-f788d215.so.2.1
ssh2_python312.libs/libgssapi_krb5-a7735118.so.2.2
ssh2_python312.libs/libcrypto-608e3dbc.so.1.0.2k
ssh2_python312.libs/libkrb5support-ff900cbb.so.0.1
ssh2_python312.libs/libk5crypto-19d2ee81.so.3.1
ssh2_python312.libs/libkrb5-9480970b.so.3.3
ssh2_python312.libs/libkeyutils-a0133cb5.so.1.5
ssh2_python312.libs/libssl-45d6cc3d.so.1.0.2k
